{
  "java_preferred_type": "luna",
  "launcher_version": 0,
  "boot_version": 0,
  "launcher_jar_url": "https://launcher.lunanw.com.tr/launcher/launcher/launcher.jar",
  "launcher_jar_path": "launcher.jar",
  "client_description": "Luna Network'de oynamak",
  "client_info_description": "Luna Network'de yapılacak çok şey var. Şimdi keşfet!",
  "client_optifine": "1.8.9 OptiFine Ultra",
  "client_version": "1.8.9",
  "launcher_title": "Luna Network Minecraft Launcher",
  "tabs": ["H A B E R L E R", "A Y A R L A R"],
  "status_loading_fonts": "Fontlar Yükleniyor...",
  "status_launching": "Launcher Başlatılıyor...",
  "status": "Bekliyor..."
}
